Metadata-Version: 2.1
Name: pyannotating
Version: 1.3.0
Summary: Library of annotations for humans
Home-page: https://github.com/TheArtur128/Pyannotating
Download-URL: https://github.com/TheArtur128/Pyannotating/archive/refs/tags/v1.3.0.zip
Author: Arthur
Author-email: s9339307190@gmail.com
License: GNU General Public License v3.0
Keywords: library,annotations,generation,templating,annotations,informing,code-readability
Classifier: Programming Language :: Python :: 3.11
Requires-Python: >=3.11
License-File: LICENSE
